{
	"info": {
		"_postman_id": "9b66fc80-5597-459a-be65-cc5e9718c8b1",
		"name": "collection.json",
		"schema": "https://schema.getpostman.com/json/collection/v2.1.0/collection.json",
		"_exporter_id": "39474296"
	},
	"item": [
		{
			"name": "GET/notes/notename",
			"request": {
				"method": "GET",
				"header": [],
				"url": {
					"raw": "http://localhost:3000/notes/Test1",
					"protocol": "http",
					"host": [
						"localhost"
					],
					"port": "3000",
					"path": [
						"notes",
						"Test1"
					]
				}
			},
			"response": []
		},
		{
			"name": "GET/UploadForm.html",
			"request": {
				"method": "GET",
				"header": [],
				"url": {
					"raw": "http://localhost:3000/UploadForm.html",
					"protocol": "http",
					"host": [
						"localhost"
					],
					"port": "3000",
					"path": [
						"UploadForm.html"
					]
				}
			},
			"response": []
		},
		{
			"name": "POST/write",
			"request": {
				"method": "POST",
				"header": [],
				"body": {
					"mode": "raw",
					"raw": "{\r\n    \"note_name\": \"New Note\",\r\n    \"note\": \"New text note\"\r\n}",
					"options": {
						"raw": {
							"language": "json"
						}
					}
				},
				"url": {
					"raw": "http://localhost:3000/write",
					"protocol": "http",
					"host": [
						"localhost"
					],
					"port": "3000",
					"path": [
						"write"
					]
				}
			},
			"response": []
		},
		{
			"name": "PUT/notes/notename",
			"request": {
				"method": "PUT",
				"header": [],
				"body": {
					"mode": "raw",
					"raw": "{\r\n    \"text\": \"Some new note text\"\r\n}",
					"options": {
						"raw": {
							"language": "json"
						}
					}
				},
				"url": {
					"raw": "http://localhost:3000/notes/Test1",
					"protocol": "http",
					"host": [
						"localhost"
					],
					"port": "3000",
					"path": [
						"notes",
						"Test1"
					]
				}
			},
			"response": []
		},
		{
			"name": "GET/notes",
			"request": {
				"method": "GET",
				"header": []
			},
			"response": []
		}
	]
}